funniest/__init__.py
funniest/command_line.py
funniest/data.json
funniest/text.py
funniest_luigib-0.1.1.dist-info/METADATA
funniest_luigib-0.1.1.dist-info/WHEEL
funniest_luigib-0.1.1.dist-info/entry_points.txt
funniest_luigib-0.1.1.dist-info/top_level.txt
funniest_luigib-0.1.1.dist-info/RECORD
